<?xml version="1.0" encoding="UTF-8"?><record_update table="catalog_ui_policy_action">
    <catalog_ui_policy_action action="INSERT_OR_UPDATE">
        <catalog_item display_value="Renew Certificate">9e85ab541b1595102369eb1cad4bcb62</catalog_item>
        <catalog_variable>IO:157073141b5595102369eb1cad4bcbdc</catalog_variable>
        <cleared>false</cleared>
        <disabled>ignore</disabled>
        <field/>
        <mandatory>ignore</mandatory>
        <order>110</order>
        <sys_class_name>catalog_ui_policy_action</sys_class_name>
        <sys_created_by>admin</sys_created_by>
        <sys_created_on>2023-04-20 10:42:50</sys_created_on>
        <sys_customer_update>false</sys_customer_update>
        <sys_id>c0a85b75db92615016a0285b139619a9</sys_id>
        <sys_mod_count>0</sys_mod_count>
        <sys_name>email_address</sys_name>
        <sys_package display_value="AppViewX" source="x_avx_appviewx_aut">7165e2f81bc808502369eb1cad4bcbe0</sys_package>
        <sys_policy/>
        <sys_replace_on_upgrade>false</sys_replace_on_upgrade>
        <sys_scope display_value="AppViewX">7165e2f81bc808502369eb1cad4bcbe0</sys_scope>
        <sys_update_name>catalog_ui_policy_action_c0a85b75db92615016a0285b139619a9</sys_update_name>
        <sys_updated_by>admin</sys_updated_by>
        <sys_updated_on>2023-04-20 10:42:50</sys_updated_on>
        <table/>
        <ui_policy display_value="Renew - To toggle the fields to Read only based on user selection">1627a85adb06155016a0285b13961998</ui_policy>
        <variable>email_address</variable>
        <variable_set/>
        <visible>true</visible>
    </catalog_ui_policy_action>
</record_update>
