<?xml version="1.0" encoding="UTF-8"?><database>
    <element db_object_id="2117f261dbf6319016a0285b13961969" label="Connection Settings Table" max_length="40" name="x_avx_appviewx_aut_connection_settings_table" type="collection">
        <element calculation="(function calculatedFieldValue(current) {&#13;&#10;&#13;&#10;&#9;// Add your code here&#13;&#10;&#9;return '';  // return the calculated value&#13;&#10;&#13;&#10;})(current);" label="Client ID" mandatory="true" max_length="100" name="client_id" type="string"/>
        <element calculation="(function calculatedFieldValue(current) {&#13;&#10;&#13;&#10;&#9;// Add your code here&#13;&#10;&#9;return '';  // return the calculated value&#13;&#10;&#13;&#10;})(current);" label="Client Secret" mandatory="true" max_length="255" name="client_secret" type="password2"/>
        <element calculation="(function calculatedFieldValue(current) {&#13;&#10;&#13;&#10;&#9;// Add your code here&#13;&#10;&#9;return '';  // return the calculated value&#13;&#10;&#13;&#10;})(current);" default="javascript:new x_avx_appviewx_aut.get_logged_in_user_company().getCompanyName()" display="true" label="Company" max_length="32" name="company" reference="core_company" type="reference"/>
        <element calculation="(function calculatedFieldValue(current) {&#13;&#10;&#13;&#10;&#9;// Add your code here&#13;&#10;&#9;return '';  // return the calculated value&#13;&#10;&#13;&#10;})(current);" label="Enable AppViewX Inventory Sync" max_length="40" name="enable_appviewx_inventory_sync" type="boolean"/>
        <element calculation="(function calculatedFieldValue(current) {&#13;&#10;&#13;&#10;&#9;// Add your code here&#13;&#10;&#9;return '';  // return the calculated value&#13;&#10;&#13;&#10;})(current);" label="Enable Log Purging" max_length="40" name="enable_log_purging" type="boolean"/>
        <element calculation="(function calculatedFieldValue(current) {&#13;&#10;&#13;&#10;&#9;// Add your code here&#13;&#10;&#9;return '';  // return the calculated value&#13;&#10;&#13;&#10;})(current);" label="Instance URL" mandatory="true" max_length="200" name="instance_url" type="string"/>
        <element calculation="(function calculatedFieldValue(current) {&#13;&#10;&#13;&#10;&#9;// Add your code here&#13;&#10;&#9;return '';  // return the calculated value&#13;&#10;&#13;&#10;})(current);" label="Log Retention Period (Days)" max_length="90" name="log_retention_period_days" type="integer"/>
        <element calculation="(function calculatedFieldValue(current) {&#13;&#10;&#13;&#10;&#9;// Add your code here&#13;&#10;&#9;return '';  // return the calculated value&#13;&#10;&#13;&#10;})(current);" label="Mid Server" max_length="100" name="mid_server" type="string"/>
        <element calculation="(function calculatedFieldValue(current) {&#13;&#10;&#13;&#10;&#9;// Add your code here&#13;&#10;&#9;return '';  // return the calculated value&#13;&#10;&#13;&#10;})(current);" label="Domain" max_length="32" name="sys_domain" type="domain_id"/>
        <element label="Domain Path" max_length="255" name="sys_domain_path" type="domain_path"/>
        <index name="index">
            <element name="company"/>
        </index>
        <index name="index2">
            <element name="sys_domain"/>
        </index>
        <index name="index3">
            <element name="sys_domain_path"/>
        </index>
    </element>
</database>
